[
  {
    "week": 0,
    "inventory": [
      5,
      12,
      12,
      16
    ],
    "backlog": [
      0,
      0,
      0,
      0
    ],
    "orders": [
      0,
      0,
      0,
      0
    ],
    "incoming": [
      0,
      0,
      0,
      0
    ],
    "operationalCost": [
      2.5,
      6,
      6,
      8
    ],
    "gas": [
      2.0080999999999998,
      2.1285499999999997,
      2.249,
      2.1994000000000002
    ],
    "systemGas": 130.80315000000002,
    "cumulativeCost": [
      2.5,
      6,
      6,
      8
    ],
    "totalGasCost": [
      2.0080999999999998,
      2.1285499999999997,
      2.249,
      2.1994000000000002
    ],
    "totalCostWithGas": [
      4.5081,
      8.12855,
      8.249,
      10.1994
    ]
  },
  {
    "week": 1,
    "inventory": [
      0,
      12,
      12,
      20
    ],
    "backlog": [
      1,
      0,
      0,
      0
    ],
    "orders": [
      1,
      0,
      0,
      0
    ],
    "incoming": [
      0,
      0,
      0,
      0
    ],
    "operationalCost": [
      1,
      6,
      6,
      10
    ],
    "gas": [
      5.0937,
      2.22855,
      2.3489999999999998,
      2.2994
    ],
    "systemGas": 132.23725000000002,
    "cumulativeCost": [
      3.5,
      12,
      12,
      18
    ],
    "totalGasCost": [
      5.0937,
      2.22855,
      2.3489999999999998,
      2.2994
    ],
    "totalCostWithGas": [
      6.0937,
      8.22855,
      8.349,
      12.2994
    ]
  },
  {
    "week": 2,
    "inventory": [
      1,
      19,
      20,
      24
    ],
    "backlog": [
      0,
      0,
      0,
      0
    ],
    "orders": [
      6,
      0,
      0,
      0
    ],
    "incoming": [
      0,
      0,
      0,
      0
    ],
    "operationalCost": [
      0.5,
      9.5,
      10,
      12
    ],
    "gas": [
      4.238700000000001,
      2.22855,
      2.3489999999999998,
      2.2994
    ],
    "systemGas": 126.97955,
    "cumulativeCost": [
      4,
      21.5,
      22,
      30
    ],
    "totalGasCost": [
      4.238700000000001,
      2.22855,
      2.3489999999999998,
      2.2994
    ],
    "totalCostWithGas": [
      4.738700000000001,
      11.72855,
      12.349,
      14.2994
    ]
  },
  {
    "week": 3,
    "inventory": [
      0,
      17,
      24,
      24
    ],
    "backlog": [
      1,
      0,
      0,
      0
    ],
    "orders": [
      5,
      0,
      0,
      0
    ],
    "incoming": [
      0,
      0,
      0,
      0
    ],
    "operationalCost": [
      1,
      8.5,
      12,
      12
    ],
    "gas": [
      4.238700000000001,
      2.22855,
      2.3489999999999998,
      2.2994
    ],
    "systemGas": 119.66050000000001,
    "cumulativeCost": [
      5,
      30,
      34,
      42
    ],
    "totalGasCost": [
      4.238700000000001,
      2.22855,
      2.3489999999999998,
      2.2994
    ],
    "totalCostWithGas": [
      5.238700000000001,
      10.72855,
      14.349,
      14.2994
    ]
  },
  {
    "week": 4,
    "inventory": [
      0,
      12,
      24,
      24
    ],
    "backlog": [
      6,
      0,
      0,
      0
    ],
    "orders": [
      6,
      0,
      0,
      0
    ],
    "incoming": [
      0,
      0,
      0,
      0
    ],
    "operationalCost": [
      6,
      6,
      12,
      12
    ],
    "gas": [
      4.238700000000001,
      2.22855,
      2.3489999999999998,
      2.2994
    ],
    "systemGas": 104.9603,
    "cumulativeCost": [
      11,
      36,
      46,
      54
    ],
    "totalGasCost": [
      4.238700000000001,
      2.22855,
      2.3489999999999998,
      2.2994
    ],
    "totalCostWithGas": [
      10.238700000000001,
      8.22855,
      14.349,
      14.2994
    ]
  },
  {
    "week": 5,
    "inventory": [
      0,
      6,
      24,
      24
    ],
    "backlog": [
      6,
      0,
      0,
      0
    ],
    "orders": [
      6,
      0,
      0,
      0
    ],
    "incoming": [
      0,
      0,
      0,
      0
    ],
    "operationalCost": [
      6,
      3,
      12,
      12
    ],
    "gas": [
      4.0987,
      2.22855,
      2.3489999999999998,
      2.2994
    ],
    "systemGas": 104.6803,
    "cumulativeCost": [
      17,
      39,
      58,
      66
    ],
    "totalGasCost": [
      4.0987,
      2.22855,
      2.3489999999999998,
      2.2994
    ],
    "totalCostWithGas": [
      10.098700000000001,
      5.22855,
      14.349,
      14.2994
    ]
  },
  {
    "week": 6,
    "inventory": [
      0,
      0,
      24,
      24
    ],
    "backlog": [
      6,
      0,
      0,
      0
    ],
    "orders": [
      5,
      0,
      0,
      0
    ],
    "incoming": [
      0,
      0,
      0,
      0
    ],
    "operationalCost": [
      6,
      0,
      12,
      12
    ],
    "gas": [
      4.238700000000001,
      2.22855,
      2.3489999999999998,
      2.2994
    ],
    "systemGas": 101.29320000000001,
    "cumulativeCost": [
      23,
      39,
      70,
      78
    ],
    "totalGasCost": [
      4.238700000000001,
      2.22855,
      2.3489999999999998,
      2.2994
    ],
    "totalCostWithGas": [
      10.238700000000001,
      2.22855,
      14.349,
      14.2994
    ]
  },
  {
    "week": 7,
    "inventory": [
      0,
      0,
      24,
      24
    ],
    "backlog": [
      6,
      5,
      0,
      0
    ],
    "orders": [
      6,
      6,
      0,
      0
    ],
    "incoming": [
      0,
      0,
      0,
      0
    ],
    "operationalCost": [
      6,
      5,
      12,
      12
    ],
    "gas": [
      4.238700000000001,
      5.21415,
      2.3489999999999998,
      2.2994
    ],
    "systemGas": 102.9231,
    "cumulativeCost": [
      29,
      44,
      82,
      90
    ],
    "totalGasCost": [
      4.238700000000001,
      5.21415,
      2.3489999999999998,
      2.2994
    ],
    "totalCostWithGas": [
      10.238700000000001,
      10.21415,
      14.349,
      14.2994
    ]
  },
  {
    "week": 8,
    "inventory": [
      0,
      0,
      18,
      24
    ],
    "backlog": [
      6,
      11,
      0,
      0
    ],
    "orders": [
      6,
      6,
      0,
      0
    ],
    "incoming": [
      0,
      0,
      0,
      0
    ],
    "operationalCost": [
      6,
      11,
      9,
      12
    ],
    "gas": [
      4.0987,
      4.21915,
      2.3489999999999998,
      2.2994
    ],
    "systemGas": 111.34985,
    "cumulativeCost": [
      35,
      55,
      91,
      102
    ],
    "totalGasCost": [
      4.0987,
      4.21915,
      2.3489999999999998,
      2.2994
    ],
    "totalCostWithGas": [
      10.098700000000001,
      15.219149999999999,
      11.349,
      14.2994
    ]
  },
  {
    "week": 9,
    "inventory": [
      0,
      0,
      12,
      24
    ],
    "backlog": [
      12,
      17,
      0,
      0
    ],
    "orders": [
      6,
      6,
      0,
      0
    ],
    "incoming": [
      0,
      0,
      0,
      0
    ],
    "operationalCost": [
      12,
      17,
      6,
      12
    ],
    "gas": [
      4.0987,
      4.21915,
      2.3489999999999998,
      2.2994
    ],
    "systemGas": 111.56660000000001,
    "cumulativeCost": [
      47,
      72,
      97,
      114
    ],
    "totalGasCost": [
      4.0987,
      4.21915,
      2.3489999999999998,
      2.2994
    ],
    "totalCostWithGas": [
      16.0987,
      21.21915,
      8.349,
      14.2994
    ]
  },
  {
    "week": 10,
    "inventory": [
      0,
      0,
      6,
      24
    ],
    "backlog": [
      17,
      17,
      0,
      0
    ],
    "orders": [
      5,
      5,
      0,
      0
    ],
    "incoming": [
      0,
      0,
      0,
      0
    ],
    "operationalCost": [
      17,
      17,
      3,
      12
    ],
    "gas": [
      4.238700000000001,
      4.35915,
      2.3489999999999998,
      2.2994
    ],
    "systemGas": 117.89025,
    "cumulativeCost": [
      64,
      89,
      100,
      126
    ],
    "totalGasCost": [
      4.238700000000001,
      4.35915,
      2.3489999999999998,
      2.2994
    ],
    "totalCostWithGas": [
      21.2387,
      21.35915,
      5.349,
      14.2994
    ]
  },
  {
    "week": 11,
    "inventory": [
      0,
      0,
      1,
      24
    ],
    "backlog": [
      23,
      16,
      0,
      0
    ],
    "orders": [
      6,
      6,
      0,
      0
    ],
    "incoming": [
      0,
      0,
      0,
      0
    ],
    "operationalCost": [
      23,
      16,
      0.5,
      12
    ],
    "gas": [
      4.238700000000001,
      4.35915,
      2.3489999999999998,
      2.2994
    ],
    "systemGas": 119.16525,
    "cumulativeCost": [
      87,
      105,
      100.5,
      138
    ],
    "totalGasCost": [
      4.238700000000001,
      4.35915,
      2.3489999999999998,
      2.2994
    ],
    "totalCostWithGas": [
      27.2387,
      20.35915,
      2.8489999999999998,
      14.2994
    ]
  },
  {
    "week": 12,
    "inventory": [
      0,
      0,
      0,
      24
    ],
    "backlog": [
      23,
      16,
      5,
      0
    ],
    "orders": [
      6,
      6,
      5,
      0
    ],
    "incoming": [
      0,
      0,
      0,
      0
    ],
    "operationalCost": [
      23,
      16,
      5,
      12
    ],
    "gas": [
      4.0987,
      4.21915,
      5.3346,
      2.2994
    ],
    "systemGas": 125.41834999999999,
    "cumulativeCost": [
      110,
      121,
      105.5,
      150
    ],
    "totalGasCost": [
      4.0987,
      4.21915,
      5.3346,
      2.2994
    ],
    "totalCostWithGas": [
      27.0987,
      20.21915,
      10.3346,
      14.2994
    ]
  },
  {
    "week": 13,
    "inventory": [
      0,
      0,
      0,
      19
    ],
    "backlog": [
      23,
      17,
      11,
      0
    ],
    "orders": [
      6,
      6,
      6,
      0
    ],
    "incoming": [
      0,
      0,
      0,
      0
    ],
    "operationalCost": [
      23,
      17,
      11,
      9.5
    ],
    "gas": [
      4.0987,
      4.21915,
      4.4796000000000005,
      2.2994
    ],
    "systemGas": 127.99865000000001,
    "cumulativeCost": [
      133,
      138,
      116.5,
      159.5
    ],
    "totalGasCost": [
      4.0987,
      4.21915,
      4.4796000000000005,
      2.2994
    ],
    "totalCostWithGas": [
      27.0987,
      21.21915,
      15.479600000000001,
      11.7994
    ]
  },
  {
    "week": 14,
    "inventory": [
      0,
      0,
      0,
      13
    ],
    "backlog": [
      23,
      22,
      17,
      0
    ],
    "orders": [
      6,
      6,
      6,
      0
    ],
    "incoming": [
      0,
      0,
      0,
      0
    ],
    "operationalCost": [
      23,
      22,
      17,
      6.5
    ],
    "gas": [
      4.0987,
      4.21915,
      4.3396,
      2.2994
    ],
    "systemGas": 128.99365,
    "cumulativeCost": [
      156,
      160,
      133.5,
      166
    ],
    "totalGasCost": [
      4.0987,
      4.21915,
      4.3396,
      2.2994
    ],
    "totalCostWithGas": [
      27.0987,
      26.21915,
      21.3396,
      8.7994
    ]
  },
  {
    "week": 15,
    "inventory": [
      0,
      0,
      0,
      7
    ],
    "backlog": [
      24,
      28,
      18,
      0
    ],
    "orders": [
      6,
      6,
      6,
      0
    ],
    "incoming": [
      0,
      0,
      0,
      0
    ],
    "operationalCost": [
      24,
      28,
      18,
      3.5
    ],
    "gas": [
      4.0987,
      4.21915,
      4.3396,
      2.2994
    ],
    "systemGas": 128.99365,
    "cumulativeCost": [
      180,
      188,
      151.5,
      169.5
    ],
    "totalGasCost": [
      4.0987,
      4.21915,
      4.3396,
      2.2994
    ],
    "totalCostWithGas": [
      28.0987,
      32.21915,
      22.3396,
      5.7994
    ]
  },
  {
    "week": 16,
    "inventory": [
      0,
      0,
      0,
      1
    ],
    "backlog": [
      30,
      34,
      18,
      0
    ],
    "orders": [
      7,
      7,
      7,
      0
    ],
    "incoming": [
      0,
      0,
      0,
      0
    ],
    "operationalCost": [
      30,
      34,
      18,
      0.5
    ],
    "gas": [
      4.238700000000001,
      4.35915,
      4.4796000000000005,
      2.2994
    ],
    "systemGas": 129.13365,
    "cumulativeCost": [
      210,
      222,
      169.5,
      170
    ],
    "totalGasCost": [
      4.238700000000001,
      4.35915,
      4.4796000000000005,
      2.2994
    ],
    "totalCostWithGas": [
      34.2387,
      38.35915,
      22.4796,
      2.7994
    ]
  },
  {
    "week": 17,
    "inventory": [
      0,
      0,
      0,
      0
    ],
    "backlog": [
      37,
      36,
      19,
      6
    ],
    "orders": [
      7,
      7,
      7,
      6
    ],
    "incoming": [
      0,
      0,
      0,
      0
    ],
    "operationalCost": [
      37,
      36,
      19,
      6
    ],
    "gas": [
      4.0987,
      4.21915,
      4.3396,
      5.285
    ],
    "systemGas": 135.9127,
    "cumulativeCost": [
      247,
      258,
      188.5,
      176
    ],
    "totalGasCost": [
      4.0987,
      4.21915,
      4.3396,
      5.285
    ],
    "totalCostWithGas": [
      41.0987,
      40.21915,
      23.3396,
      11.285
    ]
  },
  {
    "week": 18,
    "inventory": [
      0,
      0,
      0,
      0
    ],
    "backlog": [
      43,
      37,
      20,
      7
    ],
    "orders": [
      6,
      6,
      6,
      6
    ],
    "incoming": [
      0,
      0,
      0,
      0
    ],
    "operationalCost": [
      43,
      37,
      20,
      7
    ],
    "gas": [
      4.238700000000001,
      4.35915,
      4.4796000000000005,
      4.29
    ],
    "systemGas": 134.63320000000002,
    "cumulativeCost": [
      290,
      295,
      208.5,
      183
    ],
    "totalGasCost": [
      4.238700000000001,
      4.35915,
      4.4796000000000005,
      4.29
    ],
    "totalCostWithGas": [
      47.2387,
      41.35915,
      24.4796,
      11.29
    ]
  },
  {
    "week": 19,
    "inventory": [
      0,
      0,
      0,
      0
    ],
    "backlog": [
      45,
      37,
      25,
      7
    ],
    "orders": [
      7,
      7,
      7,
      7
    ],
    "incoming": [
      0,
      0,
      0,
      0
    ],
    "operationalCost": [
      45,
      37,
      25,
      7
    ],
    "gas": [
      4.238700000000001,
      4.35915,
      4.4796000000000005,
      4.43
    ],
    "systemGas": 138.51835,
    "cumulativeCost": [
      335,
      332,
      233.5,
      190
    ],
    "totalGasCost": [
      4.238700000000001,
      4.35915,
      4.4796000000000005,
      4.43
    ],
    "totalCostWithGas": [
      49.2387,
      41.35915,
      29.4796,
      11.43
    ]
  },
  {
    "week": 20,
    "inventory": [
      0,
      0,
      0,
      0
    ],
    "backlog": [
      46,
      38,
      26,
      7
    ],
    "orders": [
      7,
      7,
      7,
      7
    ],
    "incoming": [
      0,
      0,
      0,
      0
    ],
    "operationalCost": [
      46,
      38,
      26,
      7
    ],
    "gas": [
      4.0987,
      4.21915,
      4.3396,
      4.29
    ],
    "systemGas": 135.10205000000002,
    "cumulativeCost": [
      381,
      370,
      259.5,
      197
    ],
    "totalGasCost": [
      4.0987,
      4.21915,
      4.3396,
      4.29
    ],
    "totalCostWithGas": [
      50.0987,
      42.21915,
      30.3396,
      11.29
    ]
  },
  {
    "week": 21,
    "inventory": [
      0,
      0,
      0,
      0
    ],
    "backlog": [
      47,
      44,
      27,
      7
    ],
    "orders": [
      7,
      7,
      7,
      7
    ],
    "incoming": [
      0,
      0,
      0,
      0
    ],
    "operationalCost": [
      47,
      44,
      27,
      7
    ],
    "gas": [
      4.0987,
      4.21915,
      4.3396,
      4.29
    ],
    "systemGas": 135.10205000000002,
    "cumulativeCost": [
      428,
      414,
      286.5,
      204
    ],
    "totalGasCost": [
      4.0987,
      4.21915,
      4.3396,
      4.29
    ],
    "totalCostWithGas": [
      51.0987,
      48.21915,
      31.3396,
      11.29
    ]
  },
  {
    "week": 22,
    "inventory": [
      0,
      0,
      0,
      0
    ],
    "backlog": [
      47,
      45,
      27,
      7
    ],
    "orders": [
      6,
      6,
      6,
      6
    ],
    "incoming": [
      0,
      0,
      0,
      0
    ],
    "operationalCost": [
      47,
      45,
      27,
      7
    ],
    "gas": [
      4.238700000000001,
      4.35915,
      4.4796000000000005,
      4.43
    ],
    "systemGas": 135.38205,
    "cumulativeCost": [
      475,
      459,
      313.5,
      211
    ],
    "totalGasCost": [
      4.238700000000001,
      4.35915,
      4.4796000000000005,
      4.43
    ],
    "totalCostWithGas": [
      51.2387,
      49.35915,
      31.4796,
      11.43
    ]
  },
  {
    "week": 23,
    "inventory": [
      0,
      0,
      0,
      0
    ],
    "backlog": [
      53,
      45,
      26,
      7
    ],
    "orders": [
      7,
      7,
      7,
      7
    ],
    "incoming": [
      0,
      0,
      0,
      0
    ],
    "operationalCost": [
      53,
      45,
      26,
      7
    ],
    "gas": [
      4.238700000000001,
      4.35915,
      4.4796000000000005,
      4.43
    ],
    "systemGas": 138.51835,
    "cumulativeCost": [
      528,
      504,
      339.5,
      218
    ],
    "totalGasCost": [
      4.238700000000001,
      4.35915,
      4.4796000000000005,
      4.43
    ],
    "totalCostWithGas": [
      57.2387,
      49.35915,
      30.4796,
      11.43
    ]
  },
  {
    "week": 24,
    "inventory": [
      0,
      0,
      0,
      0
    ],
    "backlog": [
      55,
      45,
      26,
      7
    ],
    "orders": [
      8,
      8,
      8,
      8
    ],
    "incoming": [
      0,
      0,
      0,
      0
    ],
    "operationalCost": [
      55,
      45,
      26,
      7
    ],
    "gas": [
      4.238700000000001,
      4.35915,
      4.4796000000000005,
      4.43
    ],
    "systemGas": 135.38205,
    "cumulativeCost": [
      583,
      549,
      365.5,
      225
    ],
    "totalGasCost": [
      4.238700000000001,
      4.35915,
      4.4796000000000005,
      4.43
    ],
    "totalCostWithGas": [
      59.2387,
      49.35915,
      30.4796,
      11.43
    ]
  },
  {
    "week": 25,
    "inventory": [
      0,
      0,
      0,
      0
    ],
    "backlog": [
      57,
      46,
      28,
      7
    ],
    "orders": [
      8,
      8,
      8,
      8
    ],
    "incoming": [
      0,
      0,
      0,
      0
    ],
    "operationalCost": [
      57,
      46,
      28,
      7
    ],
    "gas": [
      4.0987,
      4.21915,
      4.3396,
      4.29
    ],
    "systemGas": 139.52225,
    "cumulativeCost": [
      640,
      595,
      393.5,
      232
    ],
    "totalGasCost": [
      4.0987,
      4.21915,
      4.3396,
      4.29
    ],
    "totalCostWithGas": [
      61.0987,
      50.21915,
      32.3396,
      11.29
    ]
  },
  {
    "week": 26,
    "inventory": [
      0,
      0,
      0,
      0
    ],
    "backlog": [
      57,
      47,
      29,
      7
    ],
    "orders": [
      7,
      7,
      7,
      7
    ],
    "incoming": [
      0,
      0,
      0,
      0
    ],
    "operationalCost": [
      57,
      47,
      29,
      7
    ],
    "gas": [
      4.238700000000001,
      4.35915,
      4.4796000000000005,
      4.43
    ],
    "systemGas": 139.80225000000002,
    "cumulativeCost": [
      697,
      642,
      422.5,
      239
    ],
    "totalGasCost": [
      4.238700000000001,
      4.35915,
      4.4796000000000005,
      4.43
    ],
    "totalCostWithGas": [
      61.2387,
      51.35915,
      33.4796,
      11.43
    ]
  },
  {
    "week": 27,
    "inventory": [
      0,
      0,
      0,
      0
    ],
    "backlog": [
      57,
      48,
      28,
      7
    ],
    "orders": [
      7,
      7,
      7,
      7
    ],
    "incoming": [
      0,
      0,
      0,
      0
    ],
    "operationalCost": [
      57,
      48,
      28,
      7
    ],
    "gas": [
      4.0987,
      4.21915,
      4.3396,
      4.29
    ],
    "systemGas": 135.10205000000002,
    "cumulativeCost": [
      754,
      690,
      450.5,
      246
    ],
    "totalGasCost": [
      4.0987,
      4.21915,
      4.3396,
      4.29
    ],
    "totalCostWithGas": [
      61.0987,
      52.21915,
      32.3396,
      11.29
    ]
  },
  {
    "week": 28,
    "inventory": [
      0,
      0,
      0,
      0
    ],
    "backlog": [
      58,
      48,
      27,
      7
    ],
    "orders": [
      8,
      8,
      8,
      8
    ],
    "incoming": [
      0,
      0,
      0,
      0
    ],
    "operationalCost": [
      58,
      48,
      27,
      7
    ],
    "gas": [
      4.238700000000001,
      4.35915,
      4.4796000000000005,
      4.43
    ],
    "systemGas": 135.66205,
    "cumulativeCost": [
      812,
      738,
      477.5,
      253
    ],
    "totalGasCost": [
      4.238700000000001,
      4.35915,
      4.4796000000000005,
      4.43
    ],
    "totalCostWithGas": [
      62.2387,
      52.35915,
      31.4796,
      11.43
    ]
  },
  {
    "week": 29,
    "inventory": [
      0,
      0,
      0,
      0
    ],
    "backlog": [
      60,
      48,
      28,
      7
    ],
    "orders": [
      8,
      8,
      8,
      8
    ],
    "incoming": [
      0,
      0,
      0,
      0
    ],
    "operationalCost": [
      60,
      48,
      28,
      7
    ],
    "gas": [
      4.0987,
      4.21915,
      4.3396,
      4.29
    ],
    "systemGas": 139.38225,
    "cumulativeCost": [
      872,
      786,
      505.5,
      260
    ],
    "totalGasCost": [
      4.0987,
      4.21915,
      4.3396,
      4.29
    ],
    "totalCostWithGas": [
      64.0987,
      52.21915,
      32.3396,
      11.29
    ]
  },
  {
    "week": 30,
    "inventory": [
      0,
      0,
      0,
      0
    ],
    "backlog": [
      60,
      48,
      29,
      7
    ],
    "orders": [
      7,
      7,
      7,
      7
    ],
    "incoming": [
      0,
      0,
      0,
      0
    ],
    "operationalCost": [
      60,
      48,
      29,
      7
    ],
    "gas": [
      4.238700000000001,
      4.35915,
      4.4796000000000005,
      4.43
    ],
    "systemGas": 139.66225,
    "cumulativeCost": [
      932,
      834,
      534.5,
      267
    ],
    "totalGasCost": [
      4.238700000000001,
      4.35915,
      4.4796000000000005,
      4.43
    ],
    "totalCostWithGas": [
      64.2387,
      52.35915,
      33.4796,
      11.43
    ]
  },
  {
    "week": 31,
    "inventory": [
      0,
      0,
      0,
      0
    ],
    "backlog": [
      60,
      48,
      28,
      7
    ],
    "orders": [
      8,
      8,
      8,
      8
    ],
    "incoming": [
      0,
      0,
      0,
      0
    ],
    "operationalCost": [
      60,
      48,
      28,
      7
    ],
    "gas": [
      4.238700000000001,
      4.35915,
      4.4796000000000005,
      4.43
    ],
    "systemGas": 135.38205,
    "cumulativeCost": [
      992,
      882,
      562.5,
      274
    ],
    "totalGasCost": [
      4.238700000000001,
      4.35915,
      4.4796000000000005,
      4.43
    ],
    "totalCostWithGas": [
      64.2387,
      52.35915,
      32.4796,
      11.43
    ]
  },
  {
    "week": 32,
    "inventory": [
      0,
      0,
      0,
      0
    ],
    "backlog": [
      61,
      49,
      28,
      7
    ],
    "orders": [
      9,
      9,
      9,
      9
    ],
    "incoming": [
      0,
      0,
      0,
      0
    ],
    "operationalCost": [
      61,
      49,
      28,
      7
    ],
    "gas": [
      4.238700000000001,
      4.35915,
      4.4796000000000005,
      4.43
    ],
    "systemGas": 139.94225,
    "cumulativeCost": [
      1053,
      931,
      590.5,
      281
    ],
    "totalGasCost": [
      4.238700000000001,
      4.35915,
      4.4796000000000005,
      4.43
    ],
    "totalCostWithGas": [
      65.2387,
      53.35915,
      32.4796,
      11.43
    ]
  },
  {
    "week": 33,
    "inventory": [
      0,
      0,
      0,
      0
    ],
    "backlog": [
      62,
      50,
      30,
      7
    ],
    "orders": [
      8,
      8,
      8,
      8
    ],
    "incoming": [
      0,
      0,
      0,
      0
    ],
    "operationalCost": [
      62,
      50,
      30,
      7
    ],
    "gas": [
      4.238700000000001,
      4.35915,
      4.4796000000000005,
      4.43
    ],
    "systemGas": 140.08225,
    "cumulativeCost": [
      1115,
      981,
      620.5,
      288
    ],
    "totalGasCost": [
      4.238700000000001,
      4.35915,
      4.4796000000000005,
      4.43
    ],
    "totalCostWithGas": [
      66.2387,
      54.35915,
      34.4796,
      11.43
    ]
  },
  {
    "week": 34,
    "inventory": [
      0,
      0,
      0,
      0
    ],
    "backlog": [
      63,
      50,
      30,
      7
    ],
    "orders": [
      8,
      8,
      8,
      8
    ],
    "incoming": [
      0,
      0,
      0,
      0
    ],
    "operationalCost": [
      63,
      50,
      30,
      7
    ],
    "gas": [
      4.0987,
      4.21915,
      4.3396,
      4.29
    ],
    "systemGas": 139.38225,
    "cumulativeCost": [
      1178,
      1031,
      650.5,
      295
    ],
    "totalGasCost": [
      4.0987,
      4.21915,
      4.3396,
      4.29
    ],
    "totalCostWithGas": [
      67.0987,
      54.21915,
      34.3396,
      11.29
    ]
  },
  {
    "week": 35,
    "inventory": [
      0,
      0,
      0,
      0
    ],
    "backlog": [
      63,
      51,
      29,
      7
    ],
    "orders": [
      8,
      8,
      8,
      8
    ],
    "incoming": [
      0,
      0,
      0,
      0
    ],
    "operationalCost": [
      63,
      51,
      29,
      7
    ],
    "gas": [
      4.0987,
      4.21915,
      4.3396,
      4.29
    ],
    "systemGas": 139.38225,
    "cumulativeCost": [
      1241,
      1082,
      679.5,
      302
    ],
    "totalGasCost": [
      4.0987,
      4.21915,
      4.3396,
      4.29
    ],
    "totalCostWithGas": [
      67.0987,
      55.21915,
      33.3396,
      11.29
    ]
  },
  {
    "week": 36,
    "inventory": [
      0,
      0,
      0,
      0
    ],
    "backlog": [
      64,
      51,
      29,
      7
    ],
    "orders": [
      9,
      9,
      9,
      9
    ],
    "incoming": [
      0,
      0,
      0,
      0
    ],
    "operationalCost": [
      64,
      51,
      29,
      7
    ],
    "gas": [
      4.238700000000001,
      4.35915,
      4.4796000000000005,
      4.43
    ],
    "systemGas": 139.80225000000002,
    "cumulativeCost": [
      1305,
      1133,
      708.5,
      309
    ],
    "totalGasCost": [
      4.238700000000001,
      4.35915,
      4.4796000000000005,
      4.43
    ],
    "totalCostWithGas": [
      68.2387,
      55.35915,
      33.4796,
      11.43
    ]
  },
  {
    "week": 37,
    "inventory": [
      0,
      0,
      0,
      0
    ],
    "backlog": [
      66,
      51,
      30,
      7
    ],
    "orders": [
      9,
      9,
      9,
      9
    ],
    "incoming": [
      0,
      0,
      0,
      0
    ],
    "operationalCost": [
      66,
      51,
      30,
      7
    ],
    "gas": [
      4.0987,
      4.21915,
      4.3396,
      4.29
    ],
    "systemGas": 139.38225,
    "cumulativeCost": [
      1371,
      1184,
      738.5,
      316
    ],
    "totalGasCost": [
      4.0987,
      4.21915,
      4.3396,
      4.29
    ],
    "totalCostWithGas": [
      70.0987,
      55.21915,
      34.3396,
      11.29
    ]
  },
  {
    "week": 38,
    "inventory": [
      0,
      0,
      0,
      0
    ],
    "backlog": [
      66,
      52,
      31,
      7
    ],
    "orders": [
      8,
      8,
      8,
      8
    ],
    "incoming": [
      0,
      0,
      0,
      0
    ],
    "operationalCost": [
      66,
      52,
      31,
      7
    ],
    "gas": [
      4.238700000000001,
      4.35915,
      4.4796000000000005,
      4.43
    ],
    "systemGas": 139.80225000000002,
    "cumulativeCost": [
      1437,
      1236,
      769.5,
      323
    ],
    "totalGasCost": [
      4.238700000000001,
      4.35915,
      4.4796000000000005,
      4.43
    ],
    "totalCostWithGas": [
      70.2387,
      56.35915,
      35.4796,
      11.43
    ]
  },
  {
    "week": 39,
    "inventory": [
      0,
      0,
      0,
      0
    ],
    "backlog": [
      65,
      52,
      30,
      7
    ],
    "orders": [
      8,
      8,
      8,
      8
    ],
    "incoming": [
      0,
      0,
      0,
      0
    ],
    "operationalCost": [
      65,
      52,
      30,
      7
    ],
    "gas": [
      4.0987,
      4.21915,
      4.3396,
      4.29
    ],
    "systemGas": 139.24225,
    "cumulativeCost": [
      1502,
      1288,
      799.5,
      330
    ],
    "totalGasCost": [
      4.0987,
      4.21915,
      4.3396,
      4.29
    ],
    "totalCostWithGas": [
      69.0987,
      56.21915,
      34.3396,
      11.29
    ]
  },
  {
    "week": 40,
    "inventory": [
      0,
      0,
      0,
      0
    ],
    "backlog": [
      67,
      52,
      29,
      7
    ],
    "orders": [
      10,
      10,
      10,
      10
    ],
    "incoming": [
      0,
      0,
      0,
      0
    ],
    "operationalCost": [
      67,
      52,
      29,
      7
    ],
    "gas": [
      4.238700000000001,
      4.35915,
      4.4796000000000005,
      4.43
    ],
    "systemGas": 139.66225,
    "cumulativeCost": [
      1569,
      1340,
      828.5,
      337
    ],
    "totalGasCost": [
      4.238700000000001,
      4.35915,
      4.4796000000000005,
      4.43
    ],
    "totalCostWithGas": [
      71.2387,
      56.35915,
      33.4796,
      11.43
    ]
  },
  {
    "week": 41,
    "inventory": [
      0,
      0,
      0,
      0
    ],
    "backlog": [
      68,
      53,
      31,
      7
    ],
    "orders": [
      9,
      9,
      9,
      9
    ],
    "incoming": [
      0,
      0,
      0,
      0
    ],
    "operationalCost": [
      68,
      53,
      31,
      7
    ],
    "gas": [
      4.238700000000001,
      4.35915,
      4.4796000000000005,
      4.43
    ],
    "systemGas": 139.94225,
    "cumulativeCost": [
      1637,
      1393,
      859.5,
      344
    ],
    "totalGasCost": [
      4.238700000000001,
      4.35915,
      4.4796000000000005,
      4.43
    ],
    "totalCostWithGas": [
      72.2387,
      57.35915,
      35.4796,
      11.43
    ]
  },
  {
    "week": 42,
    "inventory": [
      0,
      0,
      0,
      0
    ],
    "backlog": [
      68,
      53,
      32,
      7
    ],
    "orders": [
      8,
      8,
      8,
      8
    ],
    "incoming": [
      0,
      0,
      0,
      0
    ],
    "operationalCost": [
      68,
      53,
      32,
      7
    ],
    "gas": [
      4.238700000000001,
      4.35915,
      4.4796000000000005,
      4.43
    ],
    "systemGas": 139.80225000000002,
    "cumulativeCost": [
      1705,
      1446,
      891.5,
      351
    ],
    "totalGasCost": [
      4.238700000000001,
      4.35915,
      4.4796000000000005,
      4.43
    ],
    "totalCostWithGas": [
      72.2387,
      57.35915,
      36.4796,
      11.43
    ]
  },
  {
    "week": 43,
    "inventory": [
      0,
      0,
      0,
      0
    ],
    "backlog": [
      67,
      53,
      30,
      7
    ],
    "orders": [
      8,
      8,
      8,
      8
    ],
    "incoming": [
      0,
      0,
      0,
      0
    ],
    "operationalCost": [
      67,
      53,
      30,
      7
    ],
    "gas": [
      4.0987,
      4.21915,
      4.3396,
      4.29
    ],
    "systemGas": 139.38225,
    "cumulativeCost": [
      1772,
      1499,
      921.5,
      358
    ],
    "totalGasCost": [
      4.0987,
      4.21915,
      4.3396,
      4.29
    ],
    "totalCostWithGas": [
      71.0987,
      57.21915,
      34.3396,
      11.29
    ]
  },
  {
    "week": 44,
    "inventory": [
      0,
      0,
      0,
      0
    ],
    "backlog": [
      68,
      53,
      29,
      7
    ],
    "orders": [
      10,
      10,
      10,
      10
    ],
    "incoming": [
      0,
      0,
      0,
      0
    ],
    "operationalCost": [
      68,
      53,
      29,
      7
    ],
    "gas": [
      4.238700000000001,
      4.35915,
      4.4796000000000005,
      4.43
    ],
    "systemGas": 139.94225,
    "cumulativeCost": [
      1840,
      1552,
      950.5,
      365
    ],
    "totalGasCost": [
      4.238700000000001,
      4.35915,
      4.4796000000000005,
      4.43
    ],
    "totalCostWithGas": [
      72.2387,
      57.35915,
      33.4796,
      11.43
    ]
  },
  {
    "week": 45,
    "inventory": [
      0,
      0,
      0,
      0
    ],
    "backlog": [
      69,
      53,
      31,
      7
    ],
    "orders": [
      9,
      9,
      9,
      9
    ],
    "incoming": [
      0,
      0,
      0,
      0
    ],
    "operationalCost": [
      69,
      53,
      31,
      7
    ],
    "gas": [
      4.238700000000001,
      4.35915,
      4.4796000000000005,
      4.43
    ],
    "systemGas": 139.94225,
    "cumulativeCost": [
      1909,
      1605,
      981.5,
      372
    ],
    "totalGasCost": [
      4.238700000000001,
      4.35915,
      4.4796000000000005,
      4.43
    ],
    "totalCostWithGas": [
      73.2387,
      57.35915,
      35.4796,
      11.43
    ]
  },
  {
    "week": 46,
    "inventory": [
      0,
      0,
      0,
      0
    ],
    "backlog": [
      69,
      53,
      32,
      7
    ],
    "orders": [
      8,
      8,
      8,
      8
    ],
    "incoming": [
      0,
      0,
      0,
      0
    ],
    "operationalCost": [
      69,
      53,
      32,
      7
    ],
    "gas": [
      4.238700000000001,
      4.35915,
      4.4796000000000005,
      4.43
    ],
    "systemGas": 139.94225,
    "cumulativeCost": [
      1978,
      1658,
      1013.5,
      379
    ],
    "totalGasCost": [
      4.238700000000001,
      4.35915,
      4.4796000000000005,
      4.43
    ],
    "totalCostWithGas": [
      73.2387,
      57.35915,
      36.4796,
      11.43
    ]
  },
  {
    "week": 47,
    "inventory": [
      0,
      0,
      0,
      0
    ],
    "backlog": [
      67,
      53,
      30,
      7
    ],
    "orders": [
      8,
      8,
      8,
      8
    ],
    "incoming": [
      0,
      0,
      0,
      0
    ],
    "operationalCost": [
      67,
      53,
      30,
      7
    ],
    "gas": [
      4.0987,
      4.21915,
      4.3396,
      4.29
    ],
    "systemGas": 139.52225,
    "cumulativeCost": [
      2045,
      1711,
      1043.5,
      386
    ],
    "totalGasCost": [
      4.0987,
      4.21915,
      4.3396,
      4.29
    ],
    "totalCostWithGas": [
      71.0987,
      57.21915,
      34.3396,
      11.29
    ]
  },
  {
    "week": 48,
    "inventory": [
      0,
      0,
      0,
      0
    ],
    "backlog": [
      68,
      53,
      29,
      7
    ],
    "orders": [
      10,
      10,
      10,
      10
    ],
    "incoming": [
      0,
      0,
      0,
      0
    ],
    "operationalCost": [
      68,
      53,
      29,
      7
    ],
    "gas": [
      4.238700000000001,
      4.35915,
      4.4796000000000005,
      4.43
    ],
    "systemGas": 139.94225,
    "cumulativeCost": [
      2113,
      1764,
      1072.5,
      393
    ],
    "totalGasCost": [
      4.238700000000001,
      4.35915,
      4.4796000000000005,
      4.43
    ],
    "totalCostWithGas": [
      72.2387,
      57.35915,
      33.4796,
      11.43
    ]
  },
  {
    "week": 49,
    "inventory": [
      0,
      0,
      0,
      0
    ],
    "backlog": [
      66,
      53,
      31,
      7
    ],
    "orders": [
      6,
      6,
      6,
      6
    ],
    "incoming": [
      0,
      0,
      0,
      0
    ],
    "operationalCost": [
      66,
      53,
      31,
      7
    ],
    "gas": [
      4.238700000000001,
      4.35915,
      4.4796000000000005,
      4.43
    ],
    "systemGas": 139.94225,
    "cumulativeCost": [
      2179,
      1817,
      1103.5,
      400
    ],
    "totalGasCost": [
      4.238700000000001,
      4.35915,
      4.4796000000000005,
      4.43
    ],
    "totalCostWithGas": [
      70.2387,
      57.35915,
      35.4796,
      11.43
    ]
  },
  {
    "week": 50,
    "inventory": [
      0,
      0,
      0,
      0
    ],
    "backlog": [
      68,
      50,
      29,
      7
    ],
    "orders": [
      10,
      10,
      10,
      10
    ],
    "incoming": [
      0,
      0,
      0,
      0
    ],
    "operationalCost": [
      68,
      50,
      29,
      7
    ],
    "gas": [
      4.238700000000001,
      4.35915,
      4.4796000000000005,
      4.43
    ],
    "systemGas": 138.93835,
    "cumulativeCost": [
      2247,
      1867,
      1132.5,
      407
    ],
    "totalGasCost": [
      4.238700000000001,
      4.35915,
      4.4796000000000005,
      4.43
    ],
    "totalCostWithGas": [
      72.2387,
      54.35915,
      33.4796,
      11.43
    ]
  },
  {
    "week": 51,
    "inventory": [
      0,
      0,
      0,
      0
    ],
    "backlog": [
      67,
      52,
      29,
      7
    ],
    "orders": [
      9,
      9,
      9,
      9
    ],
    "incoming": [
      0,
      0,
      0,
      0
    ],
    "operationalCost": [
      67,
      52,
      29,
      7
    ],
    "gas": [
      4.238700000000001,
      4.35915,
      4.4796000000000005,
      4.43
    ],
    "systemGas": 140.08225,
    "cumulativeCost": [
      2314,
      1919,
      1161.5,
      414
    ],
    "totalGasCost": [
      4.238700000000001,
      4.35915,
      4.4796000000000005,
      4.43
    ],
    "totalCostWithGas": [
      71.2387,
      56.35915,
      33.4796,
      11.43
    ]
  },
  {
    "week": 52,
    "inventory": [
      0,
      0,
      0,
      0
    ],
    "backlog": [
      67,
      53,
      32,
      7
    ],
    "orders": [
      9,
      9,
      9,
      9
    ],
    "incoming": [
      0,
      0,
      0,
      0
    ],
    "operationalCost": [
      67,
      53,
      32,
      7
    ],
    "gas": [
      4.0987,
      4.21915,
      4.3396,
      4.29
    ],
    "systemGas": 139.52225,
    "cumulativeCost": [
      2381,
      1972,
      1193.5,
      421
    ],
    "totalGasCost": [
      4.0987,
      4.21915,
      4.3396,
      4.29
    ],
    "totalCostWithGas": [
      71.0987,
      57.21915,
      36.3396,
      11.29
    ]
  },
  {
    "week": 53,
    "inventory": [
      0,
      0,
      0,
      0
    ],
    "backlog": [
      68,
      52,
      31,
      7
    ],
    "orders": [
      9,
      9,
      9,
      9
    ],
    "incoming": [
      0,
      0,
      0,
      0
    ],
    "operationalCost": [
      68,
      52,
      31,
      7
    ],
    "gas": [
      4.0987,
      4.21915,
      4.3396,
      4.29
    ],
    "systemGas": 139.52225,
    "cumulativeCost": [
      2449,
      2024,
      1224.5,
      428
    ],
    "totalGasCost": [
      4.0987,
      4.21915,
      4.3396,
      4.29
    ],
    "totalCostWithGas": [
      72.0987,
      56.21915,
      35.3396,
      11.29
    ]
  },
  {
    "week": 54,
    "inventory": [
      0,
      0,
      0,
      0
    ],
    "backlog": [
      70,
      55,
      31,
      7
    ],
    "orders": [
      10,
      10,
      10,
      10
    ],
    "incoming": [
      0,
      0,
      0,
      0
    ],
    "operationalCost": [
      70,
      55,
      31,
      7
    ],
    "gas": [
      4.238700000000001,
      4.35915,
      4.4796000000000005,
      4.43
    ],
    "systemGas": 139.94225,
    "cumulativeCost": [
      2519,
      2079,
      1255.5,
      435
    ],
    "totalGasCost": [
      4.238700000000001,
      4.35915,
      4.4796000000000005,
      4.43
    ],
    "totalCostWithGas": [
      74.2387,
      59.35915,
      35.4796,
      11.43
    ]
  },
  {
    "week": 55,
    "inventory": [
      0,
      0,
      0,
      0
    ],
    "backlog": [
      69,
      55,
      32,
      7
    ],
    "orders": [
      9,
      9,
      9,
      9
    ],
    "incoming": [
      0,
      0,
      0,
      0
    ],
    "operationalCost": [
      69,
      55,
      32,
      7
    ],
    "gas": [
      4.238700000000001,
      4.35915,
      4.4796000000000005,
      4.43
    ],
    "systemGas": 139.94225,
    "cumulativeCost": [
      2588,
      2134,
      1287.5,
      442
    ],
    "totalGasCost": [
      4.238700000000001,
      4.35915,
      4.4796000000000005,
      4.43
    ],
    "totalCostWithGas": [
      73.2387,
      59.35915,
      36.4796,
      11.43
    ]
  },
  {
    "week": 56,
    "inventory": [
      0,
      0,
      0,
      0
    ],
    "backlog": [
      73,
      55,
      32,
      7
    ],
    "orders": [
      10,
      10,
      10,
      10
    ],
    "incoming": [
      0,
      0,
      0,
      0
    ],
    "operationalCost": [
      73,
      55,
      32,
      7
    ],
    "gas": [
      4.238700000000001,
      4.35915,
      4.4796000000000005,
      4.43
    ],
    "systemGas": 139.80225000000002,
    "cumulativeCost": [
      2661,
      2189,
      1319.5,
      449
    ],
    "totalGasCost": [
      4.238700000000001,
      4.35915,
      4.4796000000000005,
      4.43
    ],
    "totalCostWithGas": [
      77.2387,
      59.35915,
      36.4796,
      11.43
    ]
  },
  {
    "week": 57,
    "inventory": [
      0,
      0,
      0,
      0
    ],
    "backlog": [
      72,
      56,
      32,
      7
    ],
    "orders": [
      9,
      9,
      9,
      9
    ],
    "incoming": [
      0,
      0,
      0,
      0
    ],
    "operationalCost": [
      72,
      56,
      32,
      7
    ],
    "gas": [
      4.238700000000001,
      4.35915,
      4.4796000000000005,
      4.43
    ],
    "systemGas": 139.94225,
    "cumulativeCost": [
      2733,
      2245,
      1351.5,
      456
    ],
    "totalGasCost": [
      4.238700000000001,
      4.35915,
      4.4796000000000005,
      4.43
    ],
    "totalCostWithGas": [
      76.2387,
      60.35915,
      36.4796,
      11.43
    ]
  },
  {
    "week": 58,
    "inventory": [
      0,
      0,
      0,
      0
    ],
    "backlog": [
      72,
      56,
      32,
      7
    ],
    "orders": [
      9,
      9,
      9,
      9
    ],
    "incoming": [
      0,
      0,
      0,
      0
    ],
    "operationalCost": [
      72,
      56,
      32,
      7
    ],
    "gas": [
      4.0987,
      4.21915,
      4.3396,
      4.29
    ],
    "systemGas": 139.10225,
    "cumulativeCost": [
      2805,
      2301,
      1383.5,
      463
    ],
    "totalGasCost": [
      4.0987,
      4.21915,
      4.3396,
      4.29
    ],
    "totalCostWithGas": [
      76.0987,
      60.21915,
      36.3396,
      11.29
    ]
  },
  {
    "week": 59,
    "inventory": [
      0,
      0,
      0,
      0
    ],
    "backlog": [
      73,
      55,
      31,
      7
    ],
    "orders": [
      10,
      10,
      10,
      10
    ],
    "incoming": [
      0,
      0,
      0,
      0
    ],
    "operationalCost": [
      73,
      55,
      31,
      7
    ],
    "gas": [
      4.238700000000001,
      4.35915,
      4.4796000000000005,
      4.43
    ],
    "systemGas": 140.08225,
    "cumulativeCost": [
      2878,
      2356,
      1414.5,
      470
    ],
    "totalGasCost": [
      4.238700000000001,
      4.35915,
      4.4796000000000005,
      4.43
    ],
    "totalCostWithGas": [
      77.2387,
      59.35915,
      35.4796,
      11.43
    ]
  },
  {
    "week": 60,
    "inventory": [
      0,
      0,
      0,
      0
    ],
    "backlog": [
      75,
      56,
      32,
      7
    ],
    "orders": [
      11,
      11,
      11,
      11
    ],
    "incoming": [
      0,
      0,
      0,
      0
    ],
    "operationalCost": [
      75,
      56,
      32,
      7
    ],
    "gas": [
      4.238700000000001,
      4.35915,
      4.4796000000000005,
      4.43
    ],
    "systemGas": 140.22225,
    "cumulativeCost": [
      2953,
      2412,
      1446.5,
      477
    ],
    "totalGasCost": [
      4.238700000000001,
      4.35915,
      4.4796000000000005,
      4.43
    ],
    "totalCostWithGas": [
      79.2387,
      60.35915,
      36.4796,
      11.43
    ]
  },
  {
    "week": 61,
    "inventory": [
      0,
      0,
      0,
      0
    ],
    "backlog": [
      74,
      57,
      34,
      7
    ],
    "orders": [
      9,
      9,
      9,
      9
    ],
    "incoming": [
      0,
      0,
      0,
      0
    ],
    "operationalCost": [
      74,
      57,
      34,
      7
    ],
    "gas": [
      4.238700000000001,
      4.35915,
      4.4796000000000005,
      4.43
    ],
    "systemGas": 140.22225,
    "cumulativeCost": [
      3027,
      2469,
      1480.5,
      484
    ],
    "totalGasCost": [
      4.238700000000001,
      4.35915,
      4.4796000000000005,
      4.43
    ],
    "totalCostWithGas": [
      78.2387,
      61.35915,
      38.4796,
      11.43
    ]
  },
  {
    "week": 62,
    "inventory": [
      0,
      0,
      0,
      0
    ],
    "backlog": [
      74,
      57,
      33,
      7
    ],
    "orders": [
      9,
      9,
      9,
      9
    ],
    "incoming": [
      0,
      0,
      0,
      0
    ],
    "operationalCost": [
      74,
      57,
      33,
      7
    ],
    "gas": [
      4.0987,
      4.21915,
      4.3396,
      4.29
    ],
    "systemGas": 139.38225,
    "cumulativeCost": [
      3101,
      2526,
      1513.5,
      491
    ],
    "totalGasCost": [
      4.0987,
      4.21915,
      4.3396,
      4.29
    ],
    "totalCostWithGas": [
      78.0987,
      61.21915,
      37.3396,
      11.29
    ]
  },
  {
    "week": 63,
    "inventory": [
      0,
      0,
      0,
      0
    ],
    "backlog": [
      73,
      57,
      31,
      7
    ],
    "orders": [
      9,
      9,
      9,
      9
    ],
    "incoming": [
      0,
      0,
      0,
      0
    ],
    "operationalCost": [
      73,
      57,
      31,
      7
    ],
    "gas": [
      4.0987,
      4.21915,
      4.3396,
      4.29
    ],
    "systemGas": 139.38225,
    "cumulativeCost": [
      3174,
      2583,
      1544.5,
      498
    ],
    "totalGasCost": [
      4.0987,
      4.21915,
      4.3396,
      4.29
    ],
    "totalCostWithGas": [
      77.0987,
      61.21915,
      35.3396,
      11.29
    ]
  },
  {
    "week": 64,
    "inventory": [
      0,
      0,
      0,
      0
    ],
    "backlog": [
      75,
      56,
      31,
      7
    ],
    "orders": [
      11,
      11,
      11,
      11
    ],
    "incoming": [
      0,
      0,
      0,
      0
    ],
    "operationalCost": [
      75,
      56,
      31,
      7
    ],
    "gas": [
      4.238700000000001,
      4.35915,
      4.4796000000000005,
      4.43
    ],
    "systemGas": 139.80225000000002,
    "cumulativeCost": [
      3249,
      2639,
      1575.5,
      505
    ],
    "totalGasCost": [
      4.238700000000001,
      4.35915,
      4.4796000000000005,
      4.43
    ],
    "totalCostWithGas": [
      79.2387,
      60.35915,
      35.4796,
      11.43
    ]
  },
  {
    "week": 65,
    "inventory": [
      0,
      0,
      0,
      0
    ],
    "backlog": [
      75,
      56,
      33,
      7
    ],
    "orders": [
      9,
      9,
      9,
      9
    ],
    "incoming": [
      0,
      0,
      0,
      0
    ],
    "operationalCost": [
      75,
      56,
      33,
      7
    ],
    "gas": [
      4.238700000000001,
      4.35915,
      4.4796000000000005,
      4.43
    ],
    "systemGas": 139.80225000000002,
    "cumulativeCost": [
      3324,
      2695,
      1608.5,
      512
    ],
    "totalGasCost": [
      4.238700000000001,
      4.35915,
      4.4796000000000005,
      4.43
    ],
    "totalCostWithGas": [
      79.2387,
      60.35915,
      37.4796,
      11.43
    ]
  },
  {
    "week": 66,
    "inventory": [
      0,
      0,
      0,
      0
    ],
    "backlog": [
      74,
      56,
      33,
      7
    ],
    "orders": [
      9,
      9,
      9,
      9
    ],
    "incoming": [
      0,
      0,
      0,
      0
    ],
    "operationalCost": [
      74,
      56,
      33,
      7
    ],
    "gas": [
      4.0987,
      4.21915,
      4.3396,
      4.29
    ],
    "systemGas": 139.24225,
    "cumulativeCost": [
      3398,
      2751,
      1641.5,
      519
    ],
    "totalGasCost": [
      4.0987,
      4.21915,
      4.3396,
      4.29
    ],
    "totalCostWithGas": [
      78.0987,
      60.21915,
      37.3396,
      11.29
    ]
  },
  {
    "week": 67,
    "inventory": [
      0,
      0,
      0,
      0
    ],
    "backlog": [
      72,
      56,
      31,
      7
    ],
    "orders": [
      9,
      9,
      9,
      9
    ],
    "incoming": [
      0,
      0,
      0,
      0
    ],
    "operationalCost": [
      72,
      56,
      31,
      7
    ],
    "gas": [
      4.0987,
      4.21915,
      4.3396,
      4.29
    ],
    "systemGas": 139.24225,
    "cumulativeCost": [
      3470,
      2807,
      1672.5,
      526
    ],
    "totalGasCost": [
      4.0987,
      4.21915,
      4.3396,
      4.29
    ],
    "totalCostWithGas": [
      76.0987,
      60.21915,
      35.3396,
      11.29
    ]
  },
  {
    "week": 68,
    "inventory": [
      0,
      0,
      0,
      0
    ],
    "backlog": [
      73,
      56,
      31,
      7
    ],
    "orders": [
      10,
      10,
      10,
      10
    ],
    "incoming": [
      0,
      0,
      0,
      0
    ],
    "operationalCost": [
      73,
      56,
      31,
      7
    ],
    "gas": [
      4.238700000000001,
      4.35915,
      4.4796000000000005,
      4.43
    ],
    "systemGas": 139.52225,
    "cumulativeCost": [
      3543,
      2863,
      1703.5,
      533
    ],
    "totalGasCost": [
      4.238700000000001,
      4.35915,
      4.4796000000000005,
      4.43
    ],
    "totalCostWithGas": [
      77.2387,
      60.35915,
      35.4796,
      11.43
    ]
  },
  {
    "week": 69,
    "inventory": [
      0,
      0,
      0,
      0
    ],
    "backlog": [
      68,
      55,
      32,
      7
    ],
    "orders": [
      4,
      4,
      4,
      4
    ],
    "incoming": [
      0,
      0,
      0,
      0
    ],
    "operationalCost": [
      68,
      55,
      32,
      7
    ],
    "gas": [
      4.238700000000001,
      4.35915,
      4.4796000000000005,
      4.43
    ],
    "systemGas": 140.23475,
    "cumulativeCost": [
      3611,
      2918,
      1735.5,
      540
    ],
    "totalGasCost": [
      4.238700000000001,
      4.35915,
      4.4796000000000005,
      4.43
    ],
    "totalCostWithGas": [
      72.2387,
      59.35915,
      36.4796,
      11.43
    ]
  },
  {
    "week": 70,
    "inventory": [
      0,
      0,
      0,
      0
    ],
    "backlog": [
      68,
      55,
      32,
      7
    ],
    "orders": [
      0,
      0,
      0,
      0
    ],
    "incoming": [
      0,
      0,
      0,
      0
    ],
    "operationalCost": [
      68,
      55,
      32,
      7
    ],
    "gas": [
      0,
      0,
      0,
      0
    ],
    "systemGas": 0,
    "cumulativeCost": [
      3679,
      2973,
      1767.5,
      547
    ],
    "totalGasCost": [
      0,
      0,
      0,
      0
    ],
    "totalCostWithGas": [
      68,
      55,
      32,
      7
    ]
  },
  {
    "week": 71,
    "inventory": [
      0,
      0,
      0,
      0
    ],
    "backlog": [
      68,
      55,
      32,
      7
    ],
    "orders": [
      0,
      0,
      0,
      0
    ],
    "incoming": [
      0,
      0,
      0,
      0
    ],
    "operationalCost": [
      68,
      55,
      32,
      7
    ],
    "gas": [
      0,
      0,
      0,
      0
    ],
    "systemGas": 0,
    "cumulativeCost": [
      3747,
      3028,
      1799.5,
      554
    ],
    "totalGasCost": [
      0,
      0,
      0,
      0
    ],
    "totalCostWithGas": [
      68,
      55,
      32,
      7
    ]
  },
  {
    "week": 72,
    "inventory": [
      0,
      0,
      0,
      0
    ],
    "backlog": [
      68,
      55,
      32,
      7
    ],
    "orders": [
      0,
      0,
      0,
      0
    ],
    "incoming": [
      0,
      0,
      0,
      0
    ],
    "operationalCost": [
      68,
      55,
      32,
      7
    ],
    "gas": [
      0,
      0,
      0,
      0
    ],
    "systemGas": 0,
    "cumulativeCost": [
      3815,
      3083,
      1831.5,
      561
    ],
    "totalGasCost": [
      0,
      0,
      0,
      0
    ],
    "totalCostWithGas": [
      68,
      55,
      32,
      7
    ]
  },
  {
    "week": 73,
    "inventory": [
      0,
      0,
      0,
      0
    ],
    "backlog": [
      68,
      55,
      32,
      7
    ],
    "orders": [
      0,
      0,
      0,
      0
    ],
    "incoming": [
      0,
      0,
      0,
      0
    ],
    "operationalCost": [
      68,
      55,
      32,
      7
    ],
    "gas": [
      0,
      0,
      0,
      0
    ],
    "systemGas": 0,
    "cumulativeCost": [
      3883,
      3138,
      1863.5,
      568
    ],
    "totalGasCost": [
      0,
      0,
      0,
      0
    ],
    "totalCostWithGas": [
      68,
      55,
      32,
      7
    ]
  },
  {
    "week": 74,
    "inventory": [
      0,
      0,
      0,
      0
    ],
    "backlog": [
      68,
      55,
      32,
      7
    ],
    "orders": [
      0,
      0,
      0,
      0
    ],
    "incoming": [
      0,
      0,
      0,
      0
    ],
    "operationalCost": [
      68,
      55,
      32,
      7
    ],
    "gas": [
      0,
      0,
      0,
      0
    ],
    "systemGas": 0,
    "cumulativeCost": [
      3951,
      3193,
      1895.5,
      575
    ],
    "totalGasCost": [
      0,
      0,
      0,
      0
    ],
    "totalCostWithGas": [
      68,
      55,
      32,
      7
    ]
  }
]